{
  "id": "segvigen-full-auto-demo",
  "revision": 0,
  "last_node_id": 10,
  "last_link_id": 12,
  "nodes": [
    {
      "id": 1,
      "type": "LoadTrellis2Models",
      "pos": [-450, -130],
      "size": [270, 106],
      "flags": {},
      "order": 0,
      "mode": 0,
      "inputs": [
        {"localized_name": "resolution",    "name": "resolution",    "type": "COMBO", "widget": {"name": "resolution"},    "link": null},
        {"localized_name": "precision",     "name": "precision",     "type": "COMBO", "shape": 7, "widget": {"name": "precision"},     "link": null},
        {"localized_name": "attn_backend",  "name": "attn_backend",  "type": "COMBO", "shape": 7, "widget": {"name": "attn_backend"},  "link": null}
      ],
      "outputs": [
        {"localized_name": "model_config", "name": "model_config", "type": "TRELLIS2_MODEL_CONFIG", "links": [1, 2, 3], "slot_index": 0}
      ],
      "properties": {"cnr_id": "ComfyUI-TRELLIS2", "Node name for S&R": "LoadTrellis2Models"},
      "widgets_values": ["512", "auto", "auto"]
    },
    {
      "id": 2,
      "type": "LoadImage",
      "pos": [-450, 165],
      "size": [315, 314],
      "flags": {},
      "order": 1,
      "mode": 0,
      "inputs": [
        {"localized_name": "image",                  "name": "image",  "type": "COMBO",       "widget": {"name": "image"},  "link": null},
        {"localized_name": "choose file to upload",  "name": "upload", "type": "IMAGEUPLOAD", "widget": {"name": "upload"}, "link": null}
      ],
      "outputs": [
        {"localized_name": "IMAGE", "name": "IMAGE", "type": "IMAGE", "links": [4], "slot_index": 0},
        {"localized_name": "MASK",  "name": "MASK",  "type": "MASK",  "links": null}
      ],
      "properties": {"cnr_id": "comfy-core", "ver": "0.5.0", "Node name for S&R": "LoadImage"},
      "widgets_values": ["example.png", "image"]
    },
    {
      "id": 3,
      "type": "SegviGenPreprocess",
      "pos": [-90, 200],
      "size": [270, 80],
      "flags": {},
      "order": 3,
      "mode": 0,
      "inputs": [
        {"localized_name": "image",            "name": "image",            "type": "IMAGE", "link": 4},
        {"localized_name": "background_color", "name": "background_color", "type": "COMBO", "widget": {"name": "background_color"}, "link": null}
      ],
      "outputs": [
        {"localized_name": "image", "name": "image", "type": "IMAGE", "links": [5], "slot_index": 0},
        {"localized_name": "mask",  "name": "mask",  "type": "MASK",  "links": [6], "slot_index": 1}
      ],
      "properties": {"cnr_id": "ComfyUI-SegviGen", "Node name for S&R": "SegviGenPreprocess"},
      "widgets_values": ["black"]
    },
    {
      "id": 4,
      "type": "SegviGenGetConditioning",
      "pos": [230, 155],
      "size": [310, 130],
      "flags": {},
      "order": 4,
      "mode": 0,
      "inputs": [
        {"localized_name": "model_config", "name": "model_config", "type": "TRELLIS2_MODEL_CONFIG", "link": 1},
        {"localized_name": "image",        "name": "image",        "type": "IMAGE",                  "link": 5},
        {"localized_name": "mask",         "name": "mask",         "type": "MASK",                   "link": 6}
      ],
      "outputs": [
        {"localized_name": "conditioning", "name": "conditioning", "type": "SEGVIGEN_COND", "links": [8], "slot_index": 0}
      ],
      "properties": {"cnr_id": "ComfyUI-SegviGen", "Node name for S&R": "SegviGenGetConditioning"},
      "widgets_values": []
    },
    {
      "id": 5,
      "type": "SegviGenGLBtoVoxel",
      "pos": [-450, 540],
      "size": [320, 150],
      "flags": {},
      "order": 2,
      "mode": 0,
      "inputs": [
        {"localized_name": "trimesh",          "name": "trimesh",          "type": "TRIMESH", "link": null},
        {"localized_name": "glb_file",         "name": "glb_file",         "type": "COMBO",   "widget": {"name": "glb_file"},         "link": null},
        {"localized_name": "voxel_resolution", "name": "voxel_resolution", "type": "COMBO",   "widget": {"name": "voxel_resolution"}, "link": null},
        {"localized_name": "simplify_faces",   "name": "simplify_faces",   "type": "INT",     "widget": {"name": "simplify_faces"},   "link": null, "shape": 7}
      ],
      "outputs": [
        {"localized_name": "voxel", "name": "voxel", "type": "SEGVIGEN_VOXEL", "links": [7], "slot_index": 0}
      ],
      "properties": {"cnr_id": "ComfyUI-SegviGen", "Node name for S&R": "SegviGenGLBtoVoxel"},
      "widgets_values": ["output/trellis2_20260227_225733.glb", 64, 100000]
    },
    {
      "id": 6,
      "type": "SegviGenVoxelEncode",
      "pos": [-90, 540],
      "size": [310, 100],
      "flags": {},
      "order": 5,
      "mode": 0,
      "inputs": [
        {"localized_name": "model_config", "name": "model_config", "type": "TRELLIS2_MODEL_CONFIG", "link": 2},
        {"localized_name": "voxel",        "name": "voxel",        "type": "SEGVIGEN_VOXEL",        "link": 7}
      ],
      "outputs": [
        {"localized_name": "slat", "name": "slat", "type": "SEGVIGEN_SLAT", "links": [9], "slot_index": 0}
      ],
      "properties": {"cnr_id": "ComfyUI-SegviGen", "Node name for S&R": "SegviGenVoxelEncode"},
      "widgets_values": []
    },
    {
      "id": 7,
      "type": "SegviGenFullSampler",
      "pos": [580, 370],
      "size": [340, 260],
      "flags": {},
      "order": 6,
      "mode": 0,
      "inputs": [
        {"localized_name": "model_config",           "name": "model_config",           "type": "TRELLIS2_MODEL_CONFIG", "link": 3},
        {"localized_name": "slat",                   "name": "slat",                   "type": "SEGVIGEN_SLAT",         "link": 9},
        {"localized_name": "conditioning",           "name": "conditioning",           "type": "SEGVIGEN_COND",         "link": 8},
        {"localized_name": "seed",                   "name": "seed",                   "type": "INT",   "shape": 7, "widget": {"name": "seed"},                   "link": null},
        {"localized_name": "steps",                  "name": "steps",                  "type": "INT",   "shape": 7, "widget": {"name": "steps"},                  "link": null},
        {"localized_name": "guidance_strength",      "name": "guidance_strength",      "type": "FLOAT", "shape": 7, "widget": {"name": "guidance_strength"},      "link": null},
        {"localized_name": "guidance_rescale",       "name": "guidance_rescale",       "type": "FLOAT", "shape": 7, "widget": {"name": "guidance_rescale"},       "link": null},
        {"localized_name": "guidance_interval_start","name": "guidance_interval_start","type": "FLOAT", "shape": 7, "widget": {"name": "guidance_interval_start"},"link": null},
        {"localized_name": "guidance_interval_end",  "name": "guidance_interval_end",  "type": "FLOAT", "shape": 7, "widget": {"name": "guidance_interval_end"},  "link": null}
      ],
      "outputs": [
        {"localized_name": "seg_result", "name": "seg_result", "type": "SEGVIGEN_SEG_RESULT", "links": [10, 11], "slot_index": 0}
      ],
      "properties": {"cnr_id": "ComfyUI-SegviGen", "Node name for S&R": "SegviGenFullSampler"},
      "widgets_values": [0, "fixed", 12, 7.5, 0.0, 0.6, 0.9]
    },
    {
      "id": 8,
      "type": "SegviGenRenderPreview",
      "pos": [970, 260],
      "size": [270, 110],
      "flags": {},
      "order": 7,
      "mode": 0,
      "inputs": [
        {"localized_name": "seg_result", "name": "seg_result", "type": "SEGVIGEN_SEG_RESULT", "link": 10},
        {"localized_name": "num_views",  "name": "num_views",  "type": "INT", "shape": 7, "widget": {"name": "num_views"},  "link": null},
        {"localized_name": "resolution", "name": "resolution", "type": "INT", "shape": 7, "widget": {"name": "resolution"}, "link": null}
      ],
      "outputs": [
        {"localized_name": "preview_images", "name": "preview_images", "type": "IMAGE", "links": [12], "slot_index": 0}
      ],
      "properties": {"cnr_id": "ComfyUI-SegviGen", "Node name for S&R": "SegviGenRenderPreview"},
      "widgets_values": [8, 512]
    },
    {
      "id": 9,
      "type": "SaveImage",
      "pos": [1290, 260],
      "size": [260, 80],
      "flags": {},
      "order": 9,
      "mode": 0,
      "inputs": [
        {"localized_name": "images",           "name": "images",           "type": "IMAGE",  "link": 12},
        {"localized_name": "filename_prefix",  "name": "filename_prefix",  "type": "STRING", "widget": {"name": "filename_prefix"}, "link": null}
      ],
      "outputs": [],
      "properties": {"cnr_id": "comfy-core", "Node name for S&R": "SaveImage"},
      "widgets_values": ["segvigen_preview"]
    },
    {
      "id": 10,
      "type": "SegviGenExportParts",
      "pos": [970, 480],
      "size": [320, 150],
      "flags": {},
      "order": 8,
      "mode": 0,
      "inputs": [
        {"localized_name": "seg_result",        "name": "seg_result",        "type": "SEGVIGEN_SEG_RESULT", "link": 11},
        {"localized_name": "texture_size",      "name": "texture_size",      "type": "COMBO", "widget": {"name": "texture_size"},      "link": null},
        {"localized_name": "max_faces",         "name": "max_faces",         "type": "INT",   "shape": 7, "widget": {"name": "max_faces"},         "link": null},
        {"localized_name": "min_segment_faces", "name": "min_segment_faces", "type": "INT",   "shape": 7, "widget": {"name": "min_segment_faces"}, "link": null}
      ],
      "outputs": [
        {"localized_name": "output_paths", "name": "output_paths", "type": "STRING", "links": null, "slot_index": 0}
      ],
      "properties": {"cnr_id": "ComfyUI-SegviGen", "Node name for S&R": "SegviGenExportParts"},
      "widgets_values": ["2048", 100000, 50]
    }
  ],
  "links": [
    [1,  1, 0, 4,  0, "TRELLIS2_MODEL_CONFIG"],
    [2,  1, 0, 6,  0, "TRELLIS2_MODEL_CONFIG"],
    [3,  1, 0, 7,  0, "TRELLIS2_MODEL_CONFIG"],
    [4,  2, 0, 3,  0, "IMAGE"],
    [5,  3, 0, 4,  1, "IMAGE"],
    [6,  3, 1, 4,  2, "MASK"],
    [7,  5, 0, 6,  1, "SEGVIGEN_VOXEL"],
    [8,  4, 0, 7,  2, "SEGVIGEN_COND"],
    [9,  6, 0, 7,  1, "SEGVIGEN_SLAT"],
    [10, 7, 0, 8,  0, "SEGVIGEN_SEG_RESULT"],
    [11, 7, 0, 10, 0, "SEGVIGEN_SEG_RESULT"],
    [12, 8, 0, 9,  0, "IMAGE"]
  ],
  "groups": [
    {
      "title": "Image Conditioning",
      "bounding": [-470, 130, 640, 420],
      "color": "#3f789e",
      "font_size": 14
    },
    {
      "title": "Mesh → Voxel → SLAT",
      "bounding": [-470, 500, 440, 240],
      "color": "#3d6b44",
      "font_size": 14
    },
    {
      "title": "Segmentation Output",
      "bounding": [555, 340, 760, 320],
      "color": "#7e4a4a",
      "font_size": 14
    }
  ],
  "config": {},
  "extra": {
    "ds": {"scale": 0.65, "offset": [590, 230]},
    "workflowRendererVersion": "LG"
  },
  "version": 0.4
}
